scimead/__init__.py
scimead-0.0.0.dist-info/licenses/LICENSE
scimead-0.0.0.dist-info/METADATA
scimead-0.0.0.dist-info/WHEEL
scimead-0.0.0.dist-info/top_level.txt
scimead-0.0.0.dist-info/RECORD
